README.md
setup.py
fedora_distro_aliases/__init__.py
fedora_distro_aliases/cache.py
fedora_distro_aliases/cli.py
fedora_distro_aliases.egg-info/PKG-INFO
fedora_distro_aliases.egg-info/SOURCES.txt
fedora_distro_aliases.egg-info/dependency_links.txt
fedora_distro_aliases.egg-info/entry_points.txt
fedora_distro_aliases.egg-info/not-zip-safe
fedora_distro_aliases.egg-info/requires.txt
fedora_distro_aliases.egg-info/top_level.txt
tests/test_cache.py
tests/test_fedora_distro_aliases.py