Metadata-Version: 2.1
Name: fedora-distro-aliases
Version: 1.6
Summary: Aliases for active Fedora releases
Home-page: https://github.com/rpm-software-management/fedora-distro-aliases
Author: Copr and Packit teams
Author-email: copr-devel@lists.fedorahosted.org
License: GPLv2+
Requires-Dist: munch
Requires-Dist: requests
